zap_flask_pubsub/__init__.py
zap_flask_pubsub/factory.py
zap_flask_pubsub/publisher.py
zap_flask_pubsub/start_subscriber.py
zap_flask_pubsub/subscriber.py
zap_flask_pubsub/brokers/__init__.py
zap_flask_pubsub/brokers/broker.py
zap_flask_pubsub/brokers/rabbit_mq.py
zap_flask_pubsub-0.0.2.dist-info/LICENSE
zap_flask_pubsub-0.0.2.dist-info/METADATA
zap_flask_pubsub-0.0.2.dist-info/WHEEL
zap_flask_pubsub-0.0.2.dist-info/top_level.txt
zap_flask_pubsub-0.0.2.dist-info/RECORD
